Lab09/DataMemory.v
`define SIZE 1024

module DataMemory(ReadData , Address , WriteData , MemoryRead , MemoryWrite , Clock);
    input [63:0]      WriteData;
    input [63:0]      Address;
    input             Clock, MemoryRead, MemoryWrite;
    output reg [63:0] ReadData;

    reg [7:0]         memBank [`SIZE-1:0];


    // This task is used to write arbitrary data to the Data Memory by
    // the intialization block.
    task initset;
      input [63:0] addr;
      input [63:0] data;
      begin
     memBank[addr] =  data[63:56] ; // Big-endian for the win...
     memBank[addr+1] =  data[55:48];
     memBank[addr+2] =  data[47:40];
     memBank[addr+3] =  data[39:32];
     memBank[addr+4] =  data[31:24];
     memBank[addr+5] =  data[23:16];
     memBank[addr+6] =  data[15:8];
     memBank[addr+7] =  data[7:0];
      end
    endtask


    initial
    begin
        // preseting some data in the data memory used by test #1

        // Address 0x0 gets 0x1
        initset( 64'h0,  64'h1);  //Counter variable
        initset( 64'h8,  64'ha);  //Part of mask
        initset( 64'h10, 64'h5);  //Other part of mask
        initset( 64'h18, 64'h0ffbea7deadbeeff); //big constant
        initset( 64'h20, 64'h0); //clearing space

        // Add any data you need for your tests here.

    end

    // This always block reads the data memory and places a double word
    // on the ReadData bus.
    always @(posedge Clock)
    begin
        if(MemoryRead)
        begin
            ReadData[63:56] <= #20 memBank[Address];
            ReadData[55:48] <= #20 memBank[Address+1];
            ReadData[47:40] <= #20 memBank[Address+2];
            ReadData[39:32] <= #20 memBank[Address+3];
            ReadData[31:24] <= #20 memBank[Address+4];
            ReadData[23:16] <= #20 memBank[Address+5];
            ReadData[15:8] <= #20 memBank[Address+6];
            ReadData[7:0] <= #20 memBank[Address+7];
        end
    end

    // This always block takes data from the WriteData bus and writes
    // it into the DataMemory.
    always @(posedge Clock)
    begin
        if(MemoryWrite)
        begin
            memBank[Address] <= #20 WriteData[63:56] ;
            memBank[Address+1] <= #20 WriteData[55:48];
            memBank[Address+2] <= #20 WriteData[47:40];
            memBank[Address+3] <= #20 WriteData[39:32];
            memBank[Address+4] <= #20 WriteData[31:24];
            memBank[Address+5] <= #20 WriteData[23:16];
            memBank[Address+6] <= #20 WriteData[15:8];
            memBank[Address+7] <= #20 WriteData[7:0];
            // Could be useful for debugging:
            // $display("Writing Address:%h Data:%h",Address, WriteData);
        end
    end
endmodule

Lab09/alu.v
`define AND   4'b0000
`define OR    4'b0001
`define ADD   4'b0010
`define SUB   4'b0110
`define PassB 4'b0111


module ALU(BusW, BusA, BusB, ALUCtrl, Zero);
    
    parameter n = 64;

    output  [n-1:0] BusW;
    input   [n-1:0] BusA, BusB;
    input   [3:0] ALUCtrl;
    output  Zero;
    
    reg     [n-1:0] BusW;
    
    always @(ALUCtrl or BusA or BusB) begin
        case(ALUCtrl)
            `AND: BusW <= #20 BusA & BusB;
            `OR: BusW <= #20 BusA | BusB;
            `ADD: BusW <= #20 BusA + BusB;
            `SUB: BusW <= #20 BusA - BusB;
            `PassB: BusW <= #20 BusB;
        endcase
    end
	
  assign #1 Zero = (BusW ? 1'b0 : 1'b1);
endmodule

Lab09/ImmGenerator.v
module SignExtender(BusImm, Imm26, Ctrl);
	output reg [63:0] BusImm;
	input [25:0] Imm26;
  	input [2:0] Ctrl;
	
	//wire extBit;
  	//assign #1 extBit = (Ctrl ? 1'b0 : Imm26[25]); //if Ctrl is 1, extend 0's. else extend 25th bit
  	//assign BusImm [63:0] = {{38{extBit}}, Imm26[25:0]};
  	
  
  	always@(Ctrl or Imm26)
    	case(Ctrl)
          3'b000 : BusImm [63:0] = {{52{Imm26[21]}},Imm26[21:10]}; //i type
          3'b001 : BusImm [63:0] = {{55{Imm26[20]}},Imm26[20:12]}; //d type
          3'b010 : BusImm [63:0] = {{38{Imm26[25]}},Imm26[25:0]}; //b type
          3'b011 : BusImm [63:0] = {{45{Imm26[23]}},Imm26[23:5]}; //cb type
          3'b100 : BusImm [63:0] = {{48{1'b0}},{Imm26[20:5]}};
          3'b101 : BusImm [63:0] = {{32{1'b0}},{Imm26[20:5]},{16{1'b0}}};
          3'b110 : BusImm [63:0] = {{16{1'b0}},{Imm26[20:5]},{32{1'b0}}};
          3'b111 :	BusImm [63:0] = {{Imm26[20:5]},{48{1'b0}}};
        endcase
endmodule

Lab09/registerfile.v
//regFile
module RegisterFile(BusA, BusB, BusW, RA, RB, RW, RegWr, Clk);
  output [63:0] BusA, BusB;				//output
  input [63:0] BusW;					//inputs
  input [4:0] RA, RB, RW;
  input RegWr, Clk;
  
  reg [63:0] registers [31:0];			//create 32 registers of 64 bits wide
  //initial registers[31] = 0;			//make reg[31] = 0
  
  assign #2 BusA = (RA==31)?0: registers[RA];		//dataflow for output A
  assign #2 BusB = (RB==31)?0: registers[RB];		//dataflow for output B
  
  always @ (negedge Clk) begin			//on the neg clock edge, if you need to write and its not reg[31], do it.
    if(RegWr)begin 
      if(RW != 5'd31)
        registers[RW] <= #3 BusW; end
    end
endmodule

Lab09/SingleCycleControl.v
//control
`define OPCODE_ANDREG 11'b?0001010???
`define OPCODE_ORRREG 11'b?0101010???
`define OPCODE_ADDREG 11'b?0?01011???
`define OPCODE_SUBREG 11'b?1?01011???

`define OPCODE_ADDIMM 11'b?0?10001??? 
`define OPCODE_SUBIMM 11'b?1?10001???

`define OPCODE_MOVZ   11'b110100101??

`define OPCODE_B      11'b?00101?????
`define OPCODE_CBZ    11'b?011010????

`define OPCODE_LDUR   11'b??111000010
`define OPCODE_STUR   11'b??111000000

module control(
    output reg reg2loc,
    output reg alusrc,
    output reg mem2reg,
    output reg regwrite,
    output reg memread,
    output reg memwrite,
    output reg branch,
    output reg uncond_branch,
    output reg [3:0] aluop,
  output reg [2:0] signop, // becomes 3 for the MOVZ
    input [10:0] opcode
);

always @(*)
begin
    casez (opcode)

        /* Add cases here for each instruction your processor supports */
		
		`OPCODE_ANDREG : begin // AND
			reg2loc       <= 1'b0;
            alusrc        <= 1'b0;
            mem2reg       <= 1'b0;
            regwrite      <= 1'b1;
            memread       <= 1'b0;
            memwrite      <= 1'b0;
            branch        <= 1'b0;
            uncond_branch <= 1'b0;
            aluop         <= 4'b0000;
            signop        <= 3'bxx;
		end
		
		`OPCODE_ORRREG : // ORR
		begin
			reg2loc       <= 1'b0;
            alusrc        <= 1'b0;
            mem2reg       <= 1'b0;
            regwrite      <= 1'b1;
            memread       <= 1'b0;
            memwrite      <= 1'b0;
            branch        <= 1'b0;
            uncond_branch <= 1'b0;
            aluop         <= 4'b0001;
            signop        <= 3'bxx;
		end
		
		`OPCODE_ADDREG : // ADDR
		begin
			reg2loc       <= 1'b0;
            alusrc        <= 1'b0;
            mem2reg       <= 1'b0;
            regwrite      <= 1'b1;
            memread       <= 1'b0;
            memwrite      <= 1'b0;
            branch        <= 1'b0;
            uncond_branch <= 1'b0;
            aluop         <= 4'b0010;
            signop        <= 3'bxx;
		end
		
		`OPCODE_SUBREG : // SUBR
		begin
			reg2loc       <= 1'b0;
            alusrc        <= 1'b0;
            mem2reg       <= 1'b0;
            regwrite      <= 1'b1;
            memread       <= 1'b0;
            memwrite      <= 1'b0;
            branch        <= 1'b0;
            uncond_branch <= 1'b0;
            aluop         <= 4'b0110;
            signop        <= 3'bxx;
		end
		
		`OPCODE_ADDIMM : // ADDI			
		begin
			reg2loc       <= 1'bx;
            alusrc        <= 1'b1;
            mem2reg       <= 1'b0;
            regwrite      <= 1'b1;
            memread       <= 1'b0;
            memwrite      <= 1'b0;
            branch        <= 1'b0;
            uncond_branch <= 1'b0;
            aluop         <= 4'b0010;
            signop        <= 3'b00;
		end
		
		`OPCODE_SUBIMM : // SUBI			
		begin
			reg2loc       <= 1'bx;
            alusrc        <= 1'b1;
            mem2reg       <= 1'b0;
            regwrite      <= 1'b1;
            memread       <= 1'b0;
            memwrite      <= 1'b0;
            branch        <= 1'b0;
            uncond_branch <= 1'b0;
            aluop         <= 4'b0110;
            signop        <= 3'b00;
		end
		
		`OPCODE_MOVZ : // MOVZ
		begin
			reg2loc       <= 1'bx;
            alusrc        <= 1'b1;
            mem2reg       <= 1'b0;
            regwrite      <= 1'b1;
            memread       <= 1'b0;
            memwrite      <= 1'b0;
            branch        <= 1'b0;
            uncond_branch <= 1'b0;
            aluop         <= 4'b0111;//passb
          signop        <= {1'b1, opcode[1:0]};
		end
		
		`OPCODE_B : // B
		begin
			reg2loc       <= 1'bx;
            alusrc        <= 1'b0;
            mem2reg       <= 1'bx;
            regwrite      <= 1'b0;
            memread       <= 1'b0;
            memwrite      <= 1'b0;
            branch        <= 1'b0;
            uncond_branch <= 1'b1;
            aluop         <= 4'b0111;
            signop        <= 3'b10;
		end
		
		`OPCODE_CBZ : // CBZ
		begin
			reg2loc       <= 1'b1;
            alusrc        <= 1'b0;
            mem2reg       <= 1'bx;
            regwrite      <= 1'b0;
            memread       <= 1'b0;
            memwrite      <= 1'b0;
            branch        <= 1'b1;
            uncond_branch <= 1'b0;
            aluop         <= 4'b0111;
            signop        <= 3'b11;
		end
		
		`OPCODE_LDUR : // LDUR
		begin
			reg2loc       <= 1'bx;
            alusrc        <= 1'b1;
            mem2reg       <= 1'b1;
            regwrite      <= 1'b1;
            memread       <= 1'b1;
            memwrite      <= 1'b0;
            branch        <= 1'b0;
            uncond_branch <= 1'b0;
            aluop         <= 4'b0010;
            signop        <= 3'b01;
		end
		
		`OPCODE_STUR : //STUR
		begin
			reg2loc       <= 1'b1;
            alusrc        <= 1'b1;
            mem2reg       <= 1'bx;
            regwrite      <= 1'b0;
            memread       <= 1'b0;
            memwrite      <= 1'b1;
            branch        <= 1'b0;
            uncond_branch <= 1'b0;
            aluop         <= 4'b0010;
            signop        <= 3'b01;
		end
		
        default : // default all dont care
        begin
            reg2loc       <= 1'bx;
            alusrc        <= 1'bx;
            mem2reg       <= 1'bx;
            regwrite      <= 1'b0;
            memread       <= 1'b0;
            memwrite      <= 1'b0;
            branch        <= 1'b0;
            uncond_branch <= 1'b0;
            aluop         <= 4'bxxxx;
            signop        <= 3'bxx;
        end
    endcase
end

endmodule

Lab09/nextpc.v
module NextPClogic(NextPC, CurrentPC, SignExtImm64, Branch, ALUZero, Uncondbranch);
      	input [63:0] CurrentPC, SignExtImm64; 
      	input Branch, ALUZero, Uncondbranch; 
      	output reg [63:0] NextPC; 
      	/* write your code here */

  		always@ (Uncondbranch or Branch or ALUZero or SignExtImm64 or CurrentPC)	//when these values change, execute block
        begin
          if(Uncondbranch | (Branch & ALUZero))										//logic for the need to branch in dataflow
           	NextPC = #3 (SignExtImm64 << 2) + CurrentPC;							//nextPC value when branch is taken
          else
           	NextPC = #2 CurrentPC + 4;												//nextPC value when branch is not taken.
        end
endmodule

Lab09/InstructionMemory.v
module InstructionMemory(Data, Address);
   parameter T_rd = 20;
   parameter MemSize = 40;
   
   output [31:0] Data;
   input [63:0]  Address;
   reg [31:0] 	 Data;
   
   /*
    * ECEN 350 Processor Test Functions
    * Texas A&M University
    */
   
   always @ (Address) begin
      case(Address)

	/* Test Program 1:
	 * Program loads constants from the data memory. Uses these constants to test
	 * the following instructions: LDUR, ORR, AND, CBZ, ADD, SUB, STUR and B.
	 * 
	 * Assembly code for test:
	 * 
	 * 0: LDUR X9, [XZR, 0x0]    //Load 1 into x9
	 * 4: LDUR X10, [XZR, 0x8]   //Load a into x10
	 * 8: LDUR X11, [XZR, 0x10]  //Load 5 into x11
	 * C: LDUR X12, [XZR, 0x18]  //Load big constant into x12
	 * 10: LDUR X13, [XZR, 0x20]  //load a 0 into X13
	 * 
	 * 14: ORR X10, X10, X11  //Create mask of 0xf
	 * 18: AND X12, X12, X10  //Mask off low order bits of big constant
	 * 
	 * loop:
	 * 1C: CBZ X12, end  //while X12 is not 0
	 * 20: ADD X13, X13, X9  //Increment counter in X13
	 * 24: SUB X12, X12, X9  //Decrement remainder of big constant in X12
	 * 28: B loop  //Repeat till X12 is 0
	 * 2C: STUR X13, [XZR, 0x20]  //store back the counter value into the memory location 0x20
	 */
	

	63'h000: Data = 32'hF84003E9;
	63'h004: Data = 32'hF84083EA;
	63'h008: Data = 32'hF84103EB;
	63'h00c: Data = 32'hF84183EC;
	63'h010: Data = 32'hF84203ED;
	63'h014: Data = 32'hAA0B014A;
	63'h018: Data = 32'h8A0A018C;
	63'h01c: Data = 32'hB400008C;
	63'h020: Data = 32'h8B0901AD;
	63'h024: Data = 32'hCB09018C;
	63'h028: Data = 32'h17FFFFFD;
	63'h02c: Data = 32'hF80203ED;
	63'h030: Data = 32'hF84203ED;  //One last load to place stored value on memdbus for test checking.

	/* Add code for your tests here */ //This is the MOVZ
	
        63'h034: Data = {11'b11010010111,16'h1234,5'h9};//movz x9 1234
        63'h038: Data = {11'b11010010110,16'h5678,5'hA};//movz x10 5678
        63'h03C: Data = {11'bx0x01011xxx,5'hA,6'h0,5'h9,5'h9};//add x9 x9 x10
        63'h040: Data = {11'b11010010101,16'h9abc,5'hA};//movz x10 9abc
        63'h044: Data = {11'bx0x01011xxx,5'hA,6'h0,5'h9,5'h9};//add x9 x9 x10
        63'h048: Data = {11'b11010010100,16'hdef0,5'hA};//movz x10 5678
        63'h04C: Data = {11'bx0x01011xxx,5'hA,6'h0,5'h9,5'h9};//add x9 x9 x10
        63'h050: Data = {11'bxx111000000,9'h28,2'h0,5'd31,5'h9};//stur x9 [xzr,0x28]
        63'h054: Data = {11'bxx111000010,9'h28,2'h0,5'd31,5'h10};//ldur x10, [xzr, 0x28]		
        63'h058: Data = {11'bxx111000010,9'h28,2'h0,5'd31,5'h10};//ldur x10, [xzr, 0x28]
        
			
	default: Data = 32'hXXXXXXXX;
      endcase
   end
endmodule

Lab09/SingleCycleProc.v
`timescale 1ns / 1ps
module singlecycle(
    input resetl,
    input [63:0] startpc,
    output reg [63:0] currentpc,
    output [63:0] dmemout,
    input CLK
);

    // Next PC connections
  wire [63:0] nextpc;     // The next PC, to be updated on clock cycle

    // Instruction Memory connections
  wire [31:0] instruction;  // The current instruction

    // Parts of instruction
    wire [4:0] rd;            // The destination register
    wire [4:0] rm;            // Operand 1
    wire [4:0] rn;            // Operand 2
    wire [10:0] opcode;

    // Control wires
    wire reg2loc;
    wire alusrc;
    wire mem2reg;
    wire regwrite;
    wire memread;
    wire memwrite;
    wire branch;
    wire uncond_branch;
    wire [3:0] aluctrl;
  	wire [2:0] signop;

    // Register file connections
    wire [63:0] regoutA;     // Output A
    wire [63:0] regoutB;     // Output B

    // ALU connections
    wire [63:0] aluout;
  	wire [63:0] inputB; //= alusrc ? extimm : regoutB;
  	assign inputB = alusrc ? extimm : regoutB;
    wire zero;

    // Sign Extender connections
    wire [63:0] extimm;
	
	//Data memory 
	//wire [63:0] readData;
	
	//registerFile
  	wire [63:0] busW;
  	assign busW = mem2reg ? dmemout : aluout;

    // PC update logic
    always @(negedge CLK)
    begin
        if (resetl)
            currentpc <= nextpc;
        else
            currentpc <= startpc;
    end

    // Parts of instruction
    assign rd = instruction[4:0];
    assign rm = instruction[9:5];
    assign rn = reg2loc ? instruction[4:0] : instruction[20:16];
    assign opcode = instruction[31:21];

  
    InstructionMemory imem(
        .Data(instruction),
        .Address(currentpc)
    );
  
  
  	//nextPC logic
	
	NextPClogic npc(
        .NextPC(nextpc),
        .CurrentPC(currentpc),
        .SignExtImm64(extimm),
        .Branch(branch),
        .ALUZero(zero),
        .Uncondbranch(uncond_branch));

  
    control control(
        .reg2loc(reg2loc),
        .alusrc(alusrc),
        .mem2reg(mem2reg),
        .regwrite(regwrite),
        .memread(memread),
        .memwrite(memwrite),
        .branch(branch),
        .uncond_branch(uncond_branch),
        .aluop(aluctrl),
        .signop(signop),
        .opcode(opcode)
    );
  
  
  	//regFile
	
    RegisterFile rf(
        .BusA(regoutA),
        .BusB(regoutB),
        .BusW(busW),
        .RA(rm),
        .RB(rn),
        .RW(instruction[4:0]),
        .RegWr(regwrite),
        .Clk(CLK)
    );
	
  
	//signExt
	
	SignExtender se(
        .BusImm(extimm),
        .Imm26(instruction[25:0]),
        .Ctrl(signop)
    );
	
	
	//ALU
	
  	ALU alu(.BusW(aluout),
       .BusA(regoutA),
       .BusB(inputB),
       .ALUCtrl(aluctrl),
       .Zero(zero)
    );
  
  
  	//dataMemory
	
  	DataMemory dmem(
        .ReadData(dmemout),
        .Address(aluout),
        .WriteData(regoutB),
        .MemoryRead(memread),
        .MemoryWrite(memwrite),
        .Clock(CLK)
    );
	
endmodule

Lab09/SingleCycleProcTest.v
`timescale 1ns / 1ps

`include "DataMemory.v"
`include "InstructionMemory.v"

`include "ImmGenerator.v"
`include "alu.v"
`include "nextpc.v"
`include "registerfile.v"

`include "SingleCycleProc.v"
`include "SingleCycleControl.v"


`define STRLEN 32
`define HalfClockPeriod 60
`define ClockPeriod `HalfClockPeriod * 2

module SingleCycleProcTest_v;

    initial
    begin
        $dumpfile("singlecycle.vcd");
        $dumpvars;
    end

    // These tasks are used to check if a given test has passed and
    // confirm that all tests passed.
    task passTest;
        input [63:0] actualOut, expectedOut;
        input [`STRLEN*8:0] testType;
        inout [7:0] 	  passed;

        if(actualOut == expectedOut) begin $display ("%s passed", testType); passed = passed + 1; end
        else $display ("%s failed: 0x%x should be 0x%x", testType, actualOut, expectedOut);
    endtask

    task allPassed;
        input [7:0] passed;
        input [7:0] numTests;

        if(passed == numTests) $display ("All tests passed");
        else $display("Some tests failed: %d of %d passed", passed, numTests);
    endtask

    // Inputs
    reg        CLK;
    reg        Reset_L;
    reg [63:0] startPC;
    reg [7:0]  passed;
    reg [15:0] watchdog;

    // Outputs
    wire [63:0] dMemOut;
    wire [63:0] currentPC;

    // Instantiate the Unit Under Test (UUT)
    singlecycle uut (
        .CLK(CLK),
        .resetl(Reset_L),
        .startpc(startPC),
        .currentpc(currentPC),
        .dmemout(dMemOut)
    );

    initial begin
        // Initialize Inputs
        Reset_L = 1;
        startPC = 0;
        passed = 0;

        // Initialize Watchdog timer
        watchdog = 0;

        // Wait for global reset
        #(1 * `ClockPeriod);
		
        // Program 1
        #1
        Reset_L = 0; startPC = 0;
        #(1 * `ClockPeriod);
        Reset_L = 1;

        // ***********************************************************
        // This while loop will continue cycling the processor until the
        // PC reaches the final instruction in the first test.  If the
        // program forms an infinite loop, never reaching the end, the
        // watchdog timer will kick in and kill simulation after 64K
        // cycles.
        // ***********************************************************

        while (currentPC < 64'h34)
        begin
           #(1 * `ClockPeriod);
          $display("CurrentPC:%h\ndMemOut:%h",currentPC,dMemOut);
        end
        #(1 * `ClockPeriod);	// One more cycle to load the pass code from the DataMemory.
        passTest(dMemOut, 64'hF, "Results of Program 1", passed);

        // ***********************************************************
        // Add your new tests here
        // ***********************************************************
		#(1 * `ClockPeriod);
      while (currentPC < 64'h5c)
        begin
           #(1 * `ClockPeriod);
          $display("CurrentPC:%h\ndMemOut:%h",currentPC,dMemOut);
        end
        #(1 * `ClockPeriod);	
      	  
      passTest(dMemOut, 64'h123456789abcdef0, "Results of Program 2", passed);
      
        // Done
        allPassed(passed, 2);   // Be sure to change the one to match
                                // the number of tests you add.
        $finish;
    end

    initial begin
        CLK = 0;
    end

    // The following is correct if clock starts at LOW level at StartTime //
    always begin
        #`HalfClockPeriod CLK = ~CLK;
        #`HalfClockPeriod CLK = ~CLK;
        watchdog = watchdog +1;
    end

    // Kill the simulation if the watchdog hits 64K cycles
    always @*
        if (watchdog == 16'hFF)
        begin
            $display("Watchdog Timer Expired.");
            $finish;
        end


endmodule

Lab09/project_1/project_1.sim/sim_1/behav/singlecycle.vcd
$date
   Thu Apr 16 15:57:37 2020
$end
$version
  13.1
$end
$timescale
  1ps
$end
$scope module SingleCycleProcTest_v $end
$var reg 1 ! CLK $end
$var reg 1 " Reset_L $end
$var reg 64 # startPC [63:0] $end
$var reg 8 $ passed [7:0] $end
$var reg 16 % watchdog [15:0] $end
$var wire 64 & dMemOut [63:0] $end
$var wire 64 ' currentPC [63:0] $end
$scope module uut $end
$var wire 1 ( resetl $end
$var wire 64 ) startpc [63:0] $end
$var reg 64 * currentpc [63:0] $end
$var wire 64 + dmemout [63:0] $end
$var wire 1 , CLK $end
$var wire 64 - nextpc [63:0] $end
$var wire 32 . instruction [31:0] $end
$var wire 5 / rd [4:0] $end
$var wire 5 0 rm [4:0] $end
$var wire 5 1 rn [4:0] $end
$var wire 11 2 opcode [10:0] $end
$var wire 1 3 reg2loc $end
$var wire 1 4 alusrc $end
$var wire 1 5 mem2reg $end
$var wire 1 6 regwrite $end
$var wire 1 7 memread $end
$var wire 1 8 memwrite $end
$var wire 1 9 branch $end
$var wire 1 : uncond_branch $end
$var wire 4 ; aluctrl [3:0] $end
$var wire 3 < signop [2:0] $end
$var wire 64 = regoutA [63:0] $end
$var wire 64 > regoutB [63:0] $end
$var wire 64 ? aluout [63:0] $end
$var wire 64 @ inputB [63:0] $end
$var wire 1 A zero $end
$var wire 64 B extimm [63:0] $end
$var wire 64 C busW [63:0] $end
$scope module imem $end
$var wire 64 D Address [63:0] $end
$var reg 32 E Data [31:0] $end
$var parameter 32 F T_rd [31:0] $end
$var parameter 32 G MemSize [31:0] $end
$upscope $end
$scope module npc $end
$var wire 64 H CurrentPC [63:0] $end
$var wire 64 I SignExtImm64 [63:0] $end
$var wire 1 J Branch $end
$var wire 1 K ALUZero $end
$var wire 1 L Uncondbranch $end
$var reg 64 M NextPC [63:0] $end
$upscope $end
$scope module control $end
$var reg 1 N reg2loc $end
$var reg 1 O alusrc $end
$var reg 1 P mem2reg $end
$var reg 1 Q regwrite $end
$var reg 1 R memread $end
$var reg 1 S memwrite $end
$var reg 1 T branch $end
$var reg 1 U uncond_branch $end
$var reg 4 V aluop [3:0] $end
$var reg 3 W signop [2:0] $end
$var wire 11 X opcode [10:0] $end
$upscope $end
$scope module rf $end
$var wire 64 Y BusA [63:0] $end
$var wire 64 Z BusB [63:0] $end
$var wire 64 [ BusW [63:0] $end
$var wire 5 \ RA [4:0] $end
$var wire 5 ] RB [4:0] $end
$var wire 5 ^ RW [4:0] $end
$var wire 1 _ RegWr $end
$var wire 1 ` Clk $end
$var reg 2048 a registers [31:0] $end
$upscope $end
$scope module se $end
$var reg 64 b BusImm [63:0] $end
$var wire 26 c Imm26 [25:0] $end
$var wire 3 d Ctrl [2:0] $end
$upscope $end
$scope module alu $end
$var wire 64 e BusA [63:0] $end
$var wire 64 f BusB [63:0] $end
$var wire 4 g ALUCtrl [3:0] $end
$var wire 1 h Zero $end
$var reg 64 i BusW [63:0] $end
$var parameter 32 j n [31:0] $end
$upscope $end
$scope module dmem $end
$var wire 64 k WriteData [63:0] $end
$var wire 64 l Address [63:0] $end
$var wire 1 m Clock $end
$var wire 1 n MemoryRead $end
$var wire 1 o MemoryWrite $end
$var reg 64 p ReadData [63:0] $end
$var reg 8192 q memBank [1023:0] $end
$scope task initset $end
$var reg 64 r addr [63:0] $end
$var reg 64 s data [63:0] $end
$upscope $end
$upscope $end
$upscope $end
$scope task passTest $end
$var reg 64 t actualOut [63:0] $end
$var reg 64 u expectedOut [63:0] $end
$var reg 257 v testType [256:0] $end
$var reg 8 w passed [7:0] $end
$upscope $end
$scope task allPassed $end
$var reg 8 x passed [7:0] $end
$var reg 8 y numTests [7:0] $end
$upscope $end
$upscope $end
$enddefinitions $end
#0
$dumpvars
0!
1"
b0 #
b0 $
b0 %
bx &
bx '
1(
b0 )
bx *
bx +
0,
bx -
bx .
bx /
bx 0
bx 1
bx 2
x3
x4
x5
x6
x7
x8
x9
x:
bx ;
bx <
bx =
bx >
bx ?
bx @
xA
bx B
bx C
bx D
bx E
b10100 F
b101000 G
bx H
bx I
xJ
xK
xL
bx M
xN
xO
xP
xQ
xR
xS
xT
xU
bx V
bx W
bx X
bx Y
bx Z
bx [
bx \
bx ]
bx ^
x_
0`
bx a
bx b
bx c
bx d
bx e
bx f
bx g
xh
bx i
b1000000 j
bx k
bx l
0m
xn
xo
bx p
bx00000000000000000000000000000000000000000000000000000000000000001111111111101110110110111110101001111101111010101111101100001111000001010000000000000000000000000000000000000000000000000000000000001010000000000000000000000000000000000000000000000000000000000000000100000000000000000000000000000000000000000000000000000000 q
b100000 r
b0 s
bx t
bx u
bx v
bx w
bx x
bx y
$end
#1000
xA
xK
xh
#2000
bx =
bx >
bx Y
bx Z
bx e
bx k
#60000
1!
1,
1`
1m
#120000
0!
b1 %
bx *
0,
0`
0m
#121000
0"
b0 #
0(
#180000
1!
1,
1`
1m
#240000
0!
b10 %
b0 '
b0 *
0,
b11111000010000000000001111101001 .
b1001 /
b11111 0
b0x00x 1
b11111000010 2
14
15
16
17
08
09
0:
b10 ;
b1 <
b0 @
b0 B
bx C
b0 D
b11111000010000000000001111101001 E
b0 H
b0 I
0J
0L
xN
1O
1P
1Q
1R
0S
0T
0U
b10 V
b1 W
b11111000010 X
bx [
b11111 \
b0x00x ]
b1001 ^
1_
0`
b0 b
b10000000000001111101001 c
b1 d
b0 f
b10 g
0m
1n
0o
#241000
1"
1(
#242000
b100 -
b0 =
bx >
b100 M
b0 Y
bx Z
b0 e
bx k
#260000
bx i
#262000
b0 ?
bx C
bx [
b0 i
b0 l
#263000
1A
1K
1h
#265000
b100 M
#300000
1!
1,
1`
1m
#320000
b1 &
b1 +
b1 C
b1 [
b1 p
#360000
0!
b11 %
b100 '
b100 *
0,
b11111000010000001000001111101010 .
b1010 /
b0x0x0 1
b1000 @
b1000 B
b100 D
b11111000010000001000001111101010 E
b100 H
b1000 I
b0x0x0 ]
b1010 ^
0`
b1000 b
b10000001000001111101010 c
b1000 f
0m
#362000
b1000 -
bx >
b1000 M
bx Z
bx k
#363000
bx0000000000000000000000000000000000000000000000000000000000000001xxxxxxxxxxxxxxxxxxxxxxxxxxxxxxxxxxxxxxxxxxxxxxxxxxxxxxxxxxxxxxxxxxxxxxxxxxxxxxxxxxxxxxxxxxxxxxxxxxxxxxxxxxxxxxxxxxxxxxxxxxxxxxxxxxxxxxxxxxxxxxxxxxxxxxxxxxxxxxxxxxxxxxxxxxxxxxxxxxxxxxxxxxxxxxxxxxxxxxxxxxxxxxxxxxxxxxxxxxxxxxxxxxxxxxxxxxxxxxxxxxxxxxxxxxxxxxxxxxxxxxxxxxxxxxxxxxxxxxxxxxxxxxxxxxxxxxxxxxxxxxxxxxxxxxxxxxxxxxxxxxxxxxxxxxxxxxxxxxxxxxxxxxxxxxxxxxxxxxxxxxxxxxxxxxxxxxxxxxxxxxxxxxxxxxxxxxxxxxxxxxxxxxxxxxxxxxxxxxxxxxxxxxxxxxxxxxxxxxxxxxxxxxxxxxxxxxxxxxxxxxxxxxxxxxxxxxxxxxxxxxxxxxxxxxxxxxxxxxxxxxxxxxxxxxxxxxxxxxxxxxxxxxxxxxxxxxxxxxxxxxxxxxxxxxxxxxxxxxxxxxxxxxxxxxxxxxxx a
#365000
b0 =
bx >
b0 Y
bx Z
b0 e
bx k
#380000
b1000 ?
b1 C
b1 [
b1000 i
b1000 l
#381000
0A
0K
0h
#383000
b1000 M
#420000
1!
1,
1`
1m
#440000
b1010 &
b1010 +
b1010 C
b1010 [
b1010 p
#480000
0!
b100 %
b1000 '
b1000 *
0,
b11111000010000010000001111101011 .
b1011 /
b0x0x1 1
b10000 @
b10000 B
b1000 D
b11111000010000010000001111101011 E
b1000 H
b10000 I
b0x0x1 ]
b1011 ^
0`
b10000 b
b10000010000001111101011 c
b10000 f
0m
#482000
b1100 -
bx >
b1100 M
bx Z
bx k
#483000
bx00000000000000000000000000000000000000000000000000000000000010100000000000000000000000000000000000000000000000000000000000000001xxxxxxxxxxxxxxxxxxxxxxxxxxxxxxxxxxxxxxxxxxxxxxxxxxxxxxxxxxxxxxxxxxxxxxxxxxxxxxxxxxxxxxxxxxxxxxxxxxxxxxxxxxxxxxxxxxxxxxxxxxxxxxxxxxxxxxxxxxxxxxxxxxxxxxxxxxxxxxxxxxxxxxxxxxxxxxxxxxxxxxxxxxxxxxxxxxxxxxxxxxxxxxxxxxxxxxxxxxxxxxxxxxxxxxxxxxxxxxxxxxxxxxxxxxxxxxxxxxxxxxxxxxxxxxxxxxxxxxxxxxxxxxxxxxxxxxxxxxxxxxxxxxxxxxxxxxxxxxxxxxxxxxxxxxxxxxxxxxxxxxxxxxxxxxxxxxxxxxxxxxxxxxxxxxxxxxxxxxxxxxxxxxxxxxxxxxxxxxxxxxxxxxxxxxxxxxxxxxxxxxxxxxxxxxxxxxxxxxxxxxxxxxxxxxxxxxxxxxxxxxxxxxxxxxxxxxxxxxxxxxxxxxxxxxxxxxxxxxxxxxxxxxxxxxxxxxxxxxxxxxxxxxxxxxxxxxxxxxxxxxxxxxxxxxxxxxxxxxxxxxxxxxxxxxxxxxxx a
#485000
b0 =
bx >
b0 Y
bx Z
b0 e
bx k
#500000
b10000 ?
b1010 C
b1010 [
b10000 i
b10000 l
#501000
0A
0K
0h
#540000
1!
1,
1`
1m
#560000
b101 &
b101 +
b101 C
b101 [
b101 p
#600000
0!
b101 %
b1100 '
b1100 *
0,
b11111000010000011000001111101100 .
b1100 /
b0xx0x 1
b11000 @
b11000 B
b1100 D
b11111000010000011000001111101100 E
b1100 H
b11000 I
b0xx0x ]
b1100 ^
0`
b11000 b
b10000011000001111101100 c
b11000 f
0m
#602000
b10000 -
bx >
b10000 M
bx Z
bx k
